wcpy/__init__.py
wcpy/main.py
wcpy/wc_core.py
wcpy/wc_extractor.py
wcpy/wc_extractor_processor.py
wcpy/nltk_data/tokenizers/punkt/english.pickle
wcpy/nltk_data/tokenizers/punkt/PY3/english.pickle
wcpy-1.2.data/data/LICENSE
wcpy-1.2.data/scripts/wc.py
wcpy-1.2.dist-info/DESCRIPTION.rst
wcpy-1.2.dist-info/METADATA
wcpy-1.2.dist-info/RECORD
wcpy-1.2.dist-info/WHEEL
wcpy-1.2.dist-info/metadata.json
wcpy-1.2.dist-info/top_level.txt
