Metadata-Version: 1.1
Name: wcpy
Version: 1.2
Summary: WordCount in Python with a lot more functionality
Home-page: https://github.com/axsauze/wcpy
Author: Alejandro Saucedo
Author-email: a@e-x.io
License: MIT
Keywords: Word count (wcpy) on steroids
Platform: UNKNOWN
Classifier: Intended Audience :: Developers
Classifier: Programming Language :: Python :: 3
Classifier: Programming Language :: Python :: 3.3
Classifier: Programming Language :: Python :: 3.4
